Memorix/Memorix.py
Memorix/__init__.py
memorix-0.0.2.dist-info/METADATA
memorix-0.0.2.dist-info/WHEEL
memorix-0.0.2.dist-info/top_level.txt
memorix-0.0.2.dist-info/RECORD
